rmbloat/ConvertUtils.py
rmbloat/CpuStatus.py
rmbloat/FfmpegChooser.py
rmbloat/FileOps.py
rmbloat/IniManager.py
rmbloat/JobHandler.py
rmbloat/Models.py
rmbloat/ProbeCache.py
rmbloat/StructuredLogger.py
rmbloat/SystemDiscovery.py
rmbloat/TranscodeThread.py
rmbloat/VideoParser.py
rmbloat/__init__.py
rmbloat/rmbloat.py
rmbloat/rmbloatd.py
rmbloat-0.8.3.dist-info/entry_points.txt
rmbloat-0.8.3.dist-info/licenses/LICENSE
rmbloat-0.8.3.dist-info/WHEEL
rmbloat-0.8.3.dist-info/METADATA
rmbloat-0.8.3.dist-info/RECORD
