Metadata-Version: 2.4
Name: rmbloat
Version: 0.8.3
Summary: An intelligent FFmpeg utility for prioritizing and converting inefficient video files (BLOAT score).
Author-email: Joe Defen <joedef@duck.com>
Requires-Python: >=3.8
Classifier: License :: OSI Approved :: MIT License
Classifier: Programming Language :: Python :: 3
Classifier: Programming Language :: Python :: 3.8
Classifier: Programming Language :: Python :: 3.9
Classifier: Programming Language :: Python :: 3.10
Classifier: Operating System :: POSIX :: Linux
Classifier: Topic :: Multimedia :: Video
License-File: LICENSE
Requires-Dist: console-window==1.4.2
Requires-Dist: ruamel.yaml>=0.18.16
Requires-Dist: ruamel.yaml.clib>=0.2.15
Requires-Dist: Send2Trash>=1.8.3
Project-URL: Homepage, https://github.com/joedefen/rmbloat
